{
"meta":{"test_sets":[],"test_metrics":[],"learn_metrics":[{"best_value":"Min","name":"RMSE"}],"launch_mode":"Train","parameters":"","iteration_count":100,"learn_sets":["learn"],"name":"experiment"},
"iterations":[
{"learn":[14.005006],"iteration":0,"passed_time":0.001969971475,"remaining_time":0.195027176},
{"learn":[13.14441192],"iteration":1,"passed_time":0.004776647737,"remaining_time":0.2340557391},
{"learn":[12.34258257],"iteration":2,"passed_time":0.007534119988,"remaining_time":0.2436032129},
{"learn":[11.64527793],"iteration":3,"passed_time":0.009817316763,"remaining_time":0.2356156023},
{"learn":[11.02766183],"iteration":4,"passed_time":0.01138022548,"remaining_time":0.2162242841},
{"learn":[10.43485794],"iteration":5,"passed_time":0.01361362466,"remaining_time":0.2132801197},
{"learn":[9.890641275],"iteration":6,"passed_time":0.01540867031,"remaining_time":0.2047151913},
{"learn":[9.492161212],"iteration":7,"passed_time":0.01938089279,"remaining_time":0.222880267},
{"learn":[9.105082953],"iteration":8,"passed_time":0.02103054299,"remaining_time":0.2126421569},
{"learn":[8.674157135],"iteration":9,"passed_time":0.02208421979,"remaining_time":0.1987579781},
{"learn":[8.341743544],"iteration":10,"passed_time":0.02300989094,"remaining_time":0.1861709358},
{"learn":[8.049372916],"iteration":11,"passed_time":0.02427070045,"remaining_time":0.1779851366},
{"learn":[7.757318612],"iteration":12,"passed_time":0.02523863198,"remaining_time":0.168904691},
{"learn":[7.522206899],"iteration":13,"passed_time":0.02631798048,"remaining_time":0.1616675944},
{"learn":[7.297756655],"iteration":14,"passed_time":0.02761775412,"remaining_time":0.1565006067},
{"learn":[7.088359431],"iteration":15,"passed_time":0.02855577422,"remaining_time":0.1499178147},
{"learn":[6.882113791],"iteration":16,"passed_time":0.02985395019,"remaining_time":0.1457575215},
{"learn":[6.704728832],"iteration":17,"passed_time":0.03073297844,"remaining_time":0.1400057907},
{"learn":[6.563881962],"iteration":18,"passed_time":0.03169473675,"remaining_time":0.1351196672},
{"learn":[6.418790279],"iteration":19,"passed_time":0.03260312851,"remaining_time":0.130412514},
{"learn":[6.315756953],"iteration":20,"passed_time":0.03348760027,"remaining_time":0.1259771629},
{"learn":[6.210157751],"iteration":21,"passed_time":0.03430023602,"remaining_time":0.1216099277},
{"learn":[6.115058449],"iteration":22,"passed_time":0.03528796406,"remaining_time":0.1181379666},
{"learn":[6.014819884],"iteration":23,"passed_time":0.03619618065,"remaining_time":0.1146212387},
{"learn":[5.93117229],"iteration":24,"passed_time":0.03715855371,"remaining_time":0.1114756611},
{"learn":[5.844857622],"iteration":25,"passed_time":0.03822191333,"remaining_time":0.1087854456},
{"learn":[5.771145213],"iteration":26,"passed_time":0.03919767347,"remaining_time":0.1059788949},
{"learn":[5.704018229],"iteration":27,"passed_time":0.04003456671,"remaining_time":0.1029460287},
{"learn":[5.665806474],"iteration":28,"passed_time":0.04089031336,"remaining_time":0.1001107672},
{"learn":[5.616500369],"iteration":29,"passed_time":0.04185991605,"remaining_time":0.09767313744},
{"learn":[5.558023666],"iteration":30,"passed_time":0.04299598128,"remaining_time":0.09570073252},
{"learn":[5.510080976],"iteration":31,"passed_time":0.04470787556,"remaining_time":0.09500423556},
{"learn":[5.468747792],"iteration":32,"passed_time":0.04582513594,"remaining_time":0.09303891236},
{"learn":[5.429275534],"iteration":33,"passed_time":0.04703787422,"remaining_time":0.09130881465},
{"learn":[5.402117324],"iteration":34,"passed_time":0.0481632766,"remaining_time":0.08944608511},
{"learn":[5.367635151],"iteration":35,"passed_time":0.04944654915,"remaining_time":0.08790497626},
{"learn":[5.345181232],"iteration":36,"passed_time":0.05043958868,"remaining_time":0.08588362397},
{"learn":[5.319151269],"iteration":37,"passed_time":0.05167498758,"remaining_time":0.08431182185},
{"learn":[5.296134146],"iteration":38,"passed_time":0.05246526615,"remaining_time":0.0820610573},
{"learn":[5.269629003],"iteration":39,"passed_time":0.05368229065,"remaining_time":0.08052343597},
{"learn":[5.251147059],"iteration":40,"passed_time":0.05470945271,"remaining_time":0.07872823682},
{"learn":[5.248003302],"iteration":41,"passed_time":0.05539298989,"remaining_time":0.07649508127},
{"learn":[5.232376509],"iteration":42,"passed_time":0.05681588356,"remaining_time":0.07531407821},
{"learn":[5.213524255],"iteration":43,"passed_time":0.05785405797,"remaining_time":0.07363243742},
{"learn":[5.189691584],"iteration":44,"passed_time":0.05894202873,"remaining_time":0.07204025733},
{"learn":[5.166052198],"iteration":45,"passed_time":0.0606249804,"remaining_time":0.07116845525},
{"learn":[5.140406659],"iteration":46,"passed_time":0.06186600503,"remaining_time":0.0697637929},
{"learn":[5.118929684],"iteration":47,"passed_time":0.06299820908,"remaining_time":0.06824805984},
{"learn":[5.108792602],"iteration":48,"passed_time":0.06435610413,"remaining_time":0.06698288389},
{"learn":[5.098141225],"iteration":49,"passed_time":0.06550919596,"remaining_time":0.06550919596},
{"learn":[5.085926393],"iteration":50,"passed_time":0.06647103023,"remaining_time":0.06386432316},
{"learn":[5.067816804],"iteration":51,"passed_time":0.06839240622,"remaining_time":0.06313145189},
{"learn":[5.049834901],"iteration":52,"passed_time":0.06949367772,"remaining_time":0.06162646892},
{"learn":[5.03838627],"iteration":53,"passed_time":0.07048269005,"remaining_time":0.06004081004},
{"learn":[5.033534248],"iteration":54,"passed_time":0.07129285269,"remaining_time":0.05833051584},
{"learn":[5.023726885],"iteration":55,"passed_time":0.07268088996,"remaining_time":0.05710641354},
{"learn":[5.01290392],"iteration":56,"passed_time":0.07371168157,"remaining_time":0.05560705803},
{"learn":[5.005569127],"iteration":57,"passed_time":0.07479054815,"remaining_time":0.05415867279},
{"learn":[4.989969032],"iteration":58,"passed_time":0.07594677972,"remaining_time":0.05277657574},
{"learn":[4.976762446],"iteration":59,"passed_time":0.07733591034,"remaining_time":0.05155727356},
{"learn":[4.967222715],"iteration":60,"passed_time":0.07826238345,"remaining_time":0.05003660581},
{"learn":[4.954407599],"iteration":61,"passed_time":0.07940638231,"remaining_time":0.04866842787},
{"learn":[4.942125056],"iteration":62,"passed_time":0.08058403796,"remaining_time":0.0473271334},
{"learn":[4.930230716],"iteration":63,"passed_time":0.08177793319,"remaining_time":0.04600008742},
{"learn":[4.921695642],"iteration":64,"passed_time":0.08427740795,"remaining_time":0.04538014274},
{"learn":[4.906405625],"iteration":65,"passed_time":0.0853412636,"remaining_time":0.04396368125},
{"learn":[4.894330248],"iteration":66,"passed_time":0.08628017698,"remaining_time":0.04249620657},
{"learn":[4.88211557],"iteration":67,"passed_time":0.08722769311,"remaining_time":0.04104832617},
{"learn":[4.877946398],"iteration":68,"passed_time":0.08838512098,"remaining_time":0.03970925725},
{"learn":[4.863182126],"iteration":69,"passed_time":0.08958200819,"remaining_time":0.03839228923},
{"learn":[4.84646533],"iteration":70,"passed_time":0.09118142371,"remaining_time":0.03724311673},
{"learn":[4.838014752],"iteration":71,"passed_time":0.0926859711,"remaining_time":0.03604454432},
{"learn":[4.82981137],"iteration":72,"passed_time":0.09419907434,"remaining_time":0.03484075352},
{"learn":[4.817094767],"iteration":73,"passed_time":0.09555554273,"remaining_time":0.03357356907},
{"learn":[4.808314151],"iteration":74,"passed_time":0.09653899989,"remaining_time":0.03217966663},
{"learn":[4.796235023],"iteration":75,"passed_time":0.09768731901,"remaining_time":0.03084862706},
{"learn":[4.784434534],"iteration":76,"passed_time":0.09929940559,"remaining_time":0.02966086141},
{"learn":[4.774402487],"iteration":77,"passed_time":0.100343356,"remaining_time":0.0283019722},
{"learn":[4.76731896],"iteration":78,"passed_time":0.1013735133,"remaining_time":0.02694738962},
{"learn":[4.75934113],"iteration":79,"passed_time":0.1027154295,"remaining_time":0.02567885737},
{"learn":[4.754106378],"iteration":80,"passed_time":0.1039401684,"remaining_time":0.02438102716},
{"learn":[4.744002932],"iteration":81,"passed_time":0.105326867,"remaining_time":0.02312053179},
{"learn":[4.731700554],"iteration":82,"passed_time":0.1070805759,"remaining_time":0.02193216615},
{"learn":[4.723284153],"iteration":83,"passed_time":0.1083012885,"remaining_time":0.02062881685},
{"learn":[4.712232782],"iteration":84,"passed_time":0.1095381389,"remaining_time":0.01933025981},
{"learn":[4.703046867],"iteration":85,"passed_time":0.1105613165,"remaining_time":0.01799835386},
{"learn":[4.698601855],"iteration":86,"passed_time":0.1125520803,"remaining_time":0.01681812694},
{"learn":[4.692429407],"iteration":87,"passed_time":0.1140384899,"remaining_time":0.01555070317},
{"learn":[4.675027364],"iteration":88,"passed_time":0.1164552836,"remaining_time":0.01439334966},
{"learn":[4.662368584],"iteration":89,"passed_time":0.1256629385,"remaining_time":0.01396254872},
{"learn":[4.646206172],"iteration":90,"passed_time":0.1287657541,"remaining_time":0.01273507458},
{"learn":[4.641245848],"iteration":91,"passed_time":0.1302423908,"remaining_time":0.01132542529},
{"learn":[4.633900435],"iteration":92,"passed_time":0.1317237604,"remaining_time":0.009914691642},
{"learn":[4.624738236],"iteration":93,"passed_time":0.1332329605,"remaining_time":0.008504231523},
{"learn":[4.612798287],"iteration":94,"passed_time":0.1343412039,"remaining_time":0.007070589679},
{"learn":[4.605222001],"iteration":95,"passed_time":0.1354922639,"remaining_time":0.005645510994},
{"learn":[4.601725912],"iteration":96,"passed_time":0.136858704,"remaining_time":0.004232743421},
{"learn":[4.59722371],"iteration":97,"passed_time":0.1383302512,"remaining_time":0.002823066352},
{"learn":[4.580235665],"iteration":98,"passed_time":0.142401215,"remaining_time":0.001438396112},
{"learn":[4.57591791],"iteration":99,"passed_time":0.1437825129,"remaining_time":0}
]}